odoo/addons/mrp_bom_current_stock/README.rst
odoo/addons/mrp_bom_current_stock/__init__.py
odoo/addons/mrp_bom_current_stock/__manifest__.py
odoo/addons/mrp_bom_current_stock/i18n/mrp_bom_current_stock.pot
odoo/addons/mrp_bom_current_stock/readme/CONTRIBUTORS.rst
odoo/addons/mrp_bom_current_stock/readme/DESCRIPTION.rst
odoo/addons/mrp_bom_current_stock/readme/USAGE.rst
odoo/addons/mrp_bom_current_stock/reports/__init__.py
odoo/addons/mrp_bom_current_stock/reports/report_mrpcurrentstock.xml
odoo/addons/mrp_bom_current_stock/reports/report_mrpcurrentstock_xlsx.py
odoo/addons/mrp_bom_current_stock/static/description/icon.png
odoo/addons/mrp_bom_current_stock/static/description/index.html
odoo/addons/mrp_bom_current_stock/tests/__init__.py
odoo/addons/mrp_bom_current_stock/tests/test_mrp_bom_current_stock.py
odoo/addons/mrp_bom_current_stock/wizard/__init__.py
odoo/addons/mrp_bom_current_stock/wizard/bom_route_current_stock.py
odoo/addons/mrp_bom_current_stock/wizard/bom_route_current_stock_view.xml
odoo12_addon_mrp_bom_current_stock-12.0.1.0.1.dist-info/METADATA
odoo12_addon_mrp_bom_current_stock-12.0.1.0.1.dist-info/WHEEL
odoo12_addon_mrp_bom_current_stock-12.0.1.0.1.dist-info/top_level.txt
odoo12_addon_mrp_bom_current_stock-12.0.1.0.1.dist-info/RECORD
